pydenji/__init__.py
pydenji/_annotate.py
pydenji/importer.py
pydenji/pathtools.py
pydenji/placeholders.py
pydenji/resourceloader.py
pydenji/uriresolver.py
pydenji/_aop/__init__.py
pydenji/_aop/intercept.py
pydenji/_inspect/__init__.py
pydenji/_inspect/getcallableargspec.py
pydenji/appcontext/__init__.py
pydenji/appcontext/aware.py
pydenji/appcontext/context.py
pydenji/appcontext/wiring.py
pydenji/config/__init__.py
pydenji/config/argwiring.py
pydenji/config/composite.py
pydenji/config/contextconfig.py
pydenji/config/provider.py
pydenji/config/pythonconfig.py
pydenji/config/quickconfig.py
pydenji/ducktypes/__init__.py
pydenji/ducktypes/annotate.py
pydenji/ducktypes/ducktype.py
pydenji/ducktypes/function_copy.py
pydenji/ducktypes/instancebuilder.py
pydenji/ducktypes/interface.py
pydenji/ducktypes/signature.py
pydenji/ducktypes/specialmethods.py
pydenji/ducktypes/test/__init__.py
pydenji/ducktypes/test/test_annotate.py
pydenji/ducktypes/test/test_ducktype.py
pydenji/ducktypes/test/test_ducktype_class.py
pydenji/ducktypes/test/test_function_copy.py
pydenji/ducktypes/test/test_instancebuilder.py
pydenji/ducktypes/test/test_signature.py
pydenji/ducktypes/test/test_special_methods.py
pydenji/lib/__init__.py
pydenji/lib/odict.py
pydenji/test/__init__.py
pydenji/test/dummymodule.py
pydenji/test/test_annotate.py
pydenji/test/test_appcontext.py
pydenji/test/test_argwiring.py
pydenji/test/test_cmdline.py
pydenji/test/test_codescraper.py
pydenji/test/test_composite_config.py
pydenji/test/test_configobj_mapping.py
pydenji/test/test_contextwiring.py
pydenji/test/test_importer.py
pydenji/test/test_interceptor.py
pydenji/test/test_overrider.py
pydenji/test/test_pathtools.py
pydenji/test/test_provider.py
pydenji/test/test_pythonconfig.py
pydenji/test/test_resourceloader.py
pydenji/test/test_uriresolver.py
pydenji/test/integration/__init__.py
pydenji/test/integration/integration_test_full_configuration.py
pydenji-0.6.0.dist-info/DESCRIPTION.rst
pydenji-0.6.0.dist-info/METADATA
pydenji-0.6.0.dist-info/RECORD
pydenji-0.6.0.dist-info/WHEEL
pydenji-0.6.0.dist-info/entry_points.txt
pydenji-0.6.0.dist-info/metadata.json
pydenji-0.6.0.dist-info/top_level.txt
