Metadata-Version: 2.0
Name: pydenji
Version: 0.6.0
Summary: Dependency Injection Toolkit
Home-page: https://github.com/alanfranz/pydenji
Author: Alan Franzoni
Author-email: username@franzoni.eu
License: Apache-2.0
Keywords: dependency injection inversion control ioc container
Platform: UNKNOWN
Requires-Dist: byteplay (==0.2)
Requires-Dist: configobj
